datamem.v
module DataMemory (
    input wire clk,
    input wire [31:0] address,
    input wire signed [31:0] write_data,
    input wire write_enable,
    input wire read_enable,
    output reg [31:0] read_data
);

// Memoria de datos
reg [31:0] memory [0:255]; // Memoria de 256 palabras de 32 bits
initial begin
        $readmemh("ProyectoCorto_data.hex", memory); // Cargar instrucciones desde un archivo hexadecimal
    end
// Lógica de escritura y lectura de memoria
always @(posedge clk)
begin
    if (write_enable)
        memory[address] <= write_data;
    if (read_enable)
        read_data <= memory[address];
end

endmodule

datamem_tb.v
`timescale 1ns / 1ps
`include "datamem.v"

module DataMemory_tb;

    // Parámetros
    parameter CLK_PERIOD = 10; // Periodo de reloj en unidades de tiempo
    
    // Señales de entrada
    reg clk;
    reg [31:0] address;
    reg [31:0] write_data;
    reg write_enable;
    reg read_enable;
    
    // Señales de salida
    wire [31:0] read_data;
    
    // Instancia del módulo DataMemory
    DataMemory data_memory (
        .clk(clk),
        .address(address),
        .write_data(write_data),
        .write_enable(write_enable),
        .read_enable(read_enable),
        .read_data(read_data)
    );
    
    initial begin
        $dumpfile("DataMemory_tb.vcd");
        $dumpvars(0, DataMemory_tb);
    end

    // Generación de reloj
    always #((CLK_PERIOD)/2) clk = ~clk;
    
    // Testbench inicial
    initial begin
        clk = 0;
        address = 0;
        write_data = 0;
        write_enable = 0;
        read_enable = 0;

        $display(" ");
        $display("Inicializando testbench de DataMemory...");
        $display(" ");

        // Escribir datos en la memoria
        #10 write_data = 32'hDEADBEEF; // Dato 1
        write_enable = 1;
        address = 32'h00000004; // Dirección 4
        #10;
        $display("[Escritura] Direccion: %h, Dato: %h", address, write_data);

        #10 write_data = 32'hCAFEBABE; // Dato 2
        address = 32'h00000008; // Dirección 8
        #10;
        $display("[Escritura] Direccion: %h, Dato: %h", address, write_data);

        write_enable = 0;

        // Leer datos de la memoria
        #10 read_enable = 1;
        address = 32'h00000004; // Leer dirección 4
        #10;
        $display("[Lectura] Direccion: %h, Dato: %h", address, read_data);

        address = 32'h00000008; // Leer dirección 8
        #10;
        $display("[Lectura] Direccion: %h, Dato: %h", address, read_data);

        read_enable = 0;

        $display(" ");
        $display("Testbench finalizado.");
        $display(" ");
        $finish;
    end

endmodule

DataMemory_tb.vcd
$date
	Wed Apr 23 10:34:24 2025
$end
$version
	Icarus Verilog
$end
$timescale
	1ps
$end
$scope module DataMemory_tb $end
$var wire 32 ! read_data [31:0] $end
$var parameter 32 " CLK_PERIOD $end
$var reg 32 # address [31:0] $end
$var reg 1 $ clk $end
$var reg 1 % read_enable $end
$var reg 32 & write_data [31:0] $end
$var reg 1 ' write_enable $end
$scope module data_memory $end
$var wire 32 ( address [31:0] $end
$var wire 1 $ clk $end
$var wire 1 % read_enable $end
$var wire 32 ) write_data [31:0] $end
$var wire 1 ' write_enable $end
$var reg 32 * read_data [31:0] $end
$upscope $end
$upscope $end
$enddefinitions $end
$comment Show the parameter values. $end
$dumpall
b1010 "
$end
#0
$dumpvars
bx *
b0 )
b0 (
0'
b0 &
0%
0$
b0 #
bx !
$end
#5000
1$
#10000
0$
b100 #
b100 (
1'
b11011110101011011011111011101111 &
b11011110101011011011111011101111 )
#15000
1$
#20000
0$
#25000
1$
#30000
0$
b1000 #
b1000 (
b11001010111111101011101010111110 &
b11001010111111101011101010111110 )
#35000
1$
#40000
0$
0'
#45000
1$
#50000
0$
b100 #
b100 (
1%
#55000
b11011110101011011011111011101111 !
b11011110101011011011111011101111 *
1$
#60000
0$
b1000 #
b1000 (
#65000
b11001010111111101011101010111110 !
b11001010111111101011101010111110 *
1$
#70000
0$
0%
