Instmemory.v
module instmemory(addr,instruct, last_instr_flag);
    input [31:0] addr;
    output [31:0] instruct;
    reg [31:0] RF [0:31]; // 32 registros de 32 bits
    output reg last_instr_flag=0; // Bandera para indicar la última instrucción
   
   initial begin
    for (integer i = 0; i < 32; i = i + 1) begin
        RF[i] = 32'hFFFFFFFF; // Inicializar registros a -1
    end
    $readmemh("Instruction_set_R_I_S_L.hex", RF);
    $display("Memory initialized:");
    end
    


    assign instruct=RF[addr]; // Asignar la instrucción correspondiente a la dirección de memoria

    always @(instruct) begin
        // Activar la bandera si se accede a la última posición de la memoria
        if (instruct == 32'hFFFFFFFF) begin
            last_instr_flag = 1;
        end
    end
endmodule

PC.v
module PC (clk,reset, pc_reg, finish_flag);
input clk, reset;
// Registro para el contador de programa
output reg [31:0] pc_reg;
input wire finish_flag;

// Lógica del contador de programa
always @(posedge clk) begin
    if (!reset && !finish_flag) begin
        pc_reg <= pc_reg + 32'h1;
    end
end

always @(posedge reset) begin
    if (reset==1) begin
        pc_reg = 32'hFFFFFFFF;
        $display("PC reset: %h", pc_reg);
    end
end
endmodule

Instmemory_tb.v
`timescale 1ns/1ps
`include "Instmemory.v"
`include "PC.v"

module Instmemory_tb;

    reg clk, reset;
    wire [31:0] pc_reg; // Salida del módulo PC
    wire [31:0] instruct; // Instrucción actual
    wire last_instr_flag; // Bandera de última instrucción

    // Instancia del módulo PC
    PC pc_counter(
        .clk(clk),
        .reset(reset),
        .pc_reg(pc_reg),
        .finish_flag(last_instr_flag) // Detener el PC cuando se alcance la última instrucción
    );

    // Instancia del módulo Instmemory
    instmemory dut(
        .addr(pc_reg), // Dirección de la instrucción actual
        .instruct(instruct),
        .last_instr_flag(last_instr_flag)
    );

    initial begin
        $dumpfile("Instmemory_tb.vcd");
        $dumpvars(0, Instmemory_tb);

        // Inicialización
        clk = 0;
        reset = 1;
        $display(" ");
        $display("Inicializando testbench de Instmemory...");
        $display(" ");
        $display("Estado inicial: reset = %b, PC = %h, instruccion = %h, last_instr_flag = %b", reset, pc_reg, instruct, last_instr_flag);
        $display(" ");
        // Desactivar reset después de un ciclo
        #10 reset = 0;
        $display("Reset desactivado");
        $display(" ");
        // Esperar a que se alcance la última instrucción
        wait (last_instr_flag == 1);
        $display(" ");
        $display("Ultima instruccion alcanzada: PC = %h, instruccion = %h, last_instr_flag = %b", pc_reg, instruct, last_instr_flag);
        $display(" ");
        // Finalización del testbench
        $display("testbench finalizado");
        $display(" ");
        $finish;
    end

    // Bloque para observar el comportamiento en cada flanco positivo del reloj
    always @(posedge clk) begin
        $display("PC = %h, instruccion = %h, last_instr_flag = %b", pc_reg, instruct, last_instr_flag);
    end

    // Generación del reloj
    always #5 clk = ~clk;

endmodule

instmemory_tb.vcd
$date
	Tue Apr 22 17:51:32 2025
$end
$version
	Icarus Verilog
$end
$timescale
	1ps
$end
$scope module Instmemory_tb $end
$var wire 32 ! pc_reg [31:0] $end
$var wire 1 " last_instr_flag $end
$var wire 32 # instruct [31:0] $end
$var reg 1 $ clk $end
$var reg 1 % reset $end
$scope module dut $end
$var wire 32 & instruct [31:0] $end
$var wire 32 ' addr [31:0] $end
$var reg 1 " last_instr_flag $end
$scope begin $ivl_for_loop0 $end
$var integer 32 ( i [31:0] $end
$upscope $end
$upscope $end
$scope module pc_counter $end
$var wire 1 $ clk $end
$var wire 1 " finish_flag $end
$var wire 1 % reset $end
$var reg 32 ) pc_reg [31:0] $end
$upscope $end
$upscope $end
$enddefinitions $end
$comment Show the parameter values. $end
$dumpall
$end
#0
$dumpvars
b11111111111111111111111111111111 )
b100000 (
b11111111111111111111111111111111 '
bx &
1%
0$
bx #
0"
b11111111111111111111111111111111 !
$end
#5000
1$
#10000
0$
0%
#15000
b1100010000001110110011 #
b1100010000001110110011 &
b0 !
b0 '
b0 )
1$
#20000
0$
#25000
b1000000010100110000010000110011 #
b1000000010100110000010000110011 &
b1 !
b1 '
b1 )
1$
#30000
0$
#35000
b10100100111010010110011 #
b10100100111010010110011 &
b10 !
b10 '
b10 )
1$
#40000
0$
#45000
b11000100110010100110011 #
b11000100110010100110011 &
b11 !
b11 '
b11 )
1$
#50000
0$
#55000
b101000010000010110010011 #
b101000010000010110010011 &
b100 !
b100 '
b100 )
1$
#60000
0$
#65000
b1100110111011000010011 #
b1100110111011000010011 &
b101 !
b101 '
b101 )
1$
#70000
0$
#75000
b100100110011010010011 #
b100100110011010010011 &
b110 !
b110 '
b110 )
1$
#80000
0$
#85000
b10000010010011100000011 #
b10000010010011100000011 &
b111 !
b111 '
b111 )
1$
#90000
0$
#95000
b111000011010010000100011 #
b111000011010010000100011 &
b1000 !
b1000 '
b1000 )
1$
#100000
0$
#105000
1"
b11111111111111111111111111111111 #
b11111111111111111111111111111111 &
b1001 !
b1001 '
b1001 )
1$
